design/control_signal_generator.v
module control_signal_generator(input [6:0] opcode,output reg reg_write,output reg mem_read,output reg mem_write,output reg alu_src,output reg branch,
output reg [1:0] alu_op);
always @(*) begin

reg_write = 0;
mem_read = 0;
mem_write = 0;
alu_src = 0;
branch = 0;
alu_op = 2'b00;

case(opcode)
7'b0110011: begin
    reg_write = 1;
    alu_src = 0;
    alu_op = 2'b10;
end
7'b0010011: begin
    reg_write = 1;
    alu_src = 1;
    alu_op = 2'b00;
end
7'b0000011: begin
    reg_write = 1;
    mem_read = 1;
    alu_src = 1;
    alu_op = 2'b00;
end
7'b0100011: begin
    mem_write = 1;
    alu_src = 1;
    alu_op = 2'b00;
end
7'b1100011: begin
    branch = 1;
    alu_src = 0;
    alu_op = 2'b01;
end
endcase
end
endmodule

design/alu_32bit.v
module alu_32bit(input [31:0] A, input [31:0] B, input [2:0] alu_sel, output reg [31:0] result);
always @(*) begin
    case(alu_sel)
        3'b000: result = A + B;
        3'b001: result = A - B;
        3'b010: result = A & B;
        3'b011: result = A | B;
        3'b100: result = A ^ B;
        3'b101: result = ~A;
        3'b110: result = A << 1;
        3'b111: result = A >> 1;
        default: result = 32'b0;
    endcase
end
endmodule

design/data_memory.v
module data_memory(input clk,input mem_read,input mem_write,input [31:0] write_data,input [31:0] address,output reg [31:0] read_data);
reg [31:0] memory[0:31];
integer i;
initial begin // removes undefined modules during simulation as earlier
    for(i = 0; i < 32; i = i + 1)
        memory[i] = 32'b0;
end
always @(posedge clk) begin
    if(mem_write)
        memory[address[4:0]] <= write_data;
end
always @(*) begin
    if(mem_read)
        read_data = memory[address[4:0]];
    else
        read_data = 32'b0;
end
endmodule

design/alu_control.v
module alu_control(input [1:0] alu_op,input [2:0] func3,input [6:0] func7,output reg [2:0] alu_sel);
always @(*) begin
    case(alu_op)
        2'b00: alu_sel = 3'b000;   // addi, lw, sw
        2'b01: alu_sel = 3'b001;   // beq 
        2'b10: begin               // R-Type
            case(func3)
                3'b000: begin
                    if(func7 == 7'b0100000)
                        alu_sel = 3'b001;// sub
                    else
                        alu_sel = 3'b000;// add
                end
                3'b111: alu_sel = 3'b010;// and
                3'b110: alu_sel = 3'b011;// or
                default: alu_sel = 3'b000;
            endcase
        end

        default: alu_sel = 3'b000;
    endcase
end
//only added these for now ADD,ADDI,SW,BEQ later XOR,SLL,SRL
endmodule

design/register_file.v
module register_file(input clk,input reg_write,input [4:0] source_reg_1,input [4:0] source_reg_2,input [4:0] destination_reg,input [31:0] write_data,output [31:0] read_data1,output [31:0] read_data2);
reg [31:0] registers[31:0];
integer i;
initial begin
    for(i=0;i<32;i=i+1)
        registers[i] = 0;
end
always @(posedge clk) begin
    if(reg_write && destination_reg != 0)
        registers[destination_reg] <= write_data;
end
assign read_data1 = (source_reg_1 == 0) ? 32'b0 : registers[source_reg_1];
assign read_data2 = (source_reg_2 == 0) ? 32'b0 : registers[source_reg_2];
endmodule

design/complete_riscv_decoder.v
module complete_riscv_decoder(input [31:0] instruction , output reg [6:0] opcode , output reg [4:0] destination_reg , output reg [2:0] func3 , output reg [4:0] source_reg_1 , output reg [ 4:0] source_reg_2 , output reg [6:0] func7 , output reg [31:0] immediate );
  always @(*)
    begin
      opcode = instruction [6:0];
      destination_reg = 0;
      func3 =0;
      source_reg_1 =0;
      source_reg_2 =0;
      func7 =0;
      immediate =0;
      case(opcode)
7'b0110011:
      begin // R TYPE
destination_reg = instruction[11:7];
func3 = instruction[14:12];
source_reg_1 = instruction[19:15];
source_reg_2 = instruction[24:20];
func7 = instruction[31:25];
end
 7'b0010011:
     begin //I TYPE
destination_reg = instruction[11:7];
func3 = instruction[14:12];
source_reg_1 = instruction[19:15];
immediate = {{20{instruction[31]}}, instruction[31:20]};
     end
7'b0100011:
      begin //S TYPE
func3 = instruction[14:12];
source_reg_1 = instruction[19:15];
source_reg_2 = instruction[24:20];
immediate = {{20{instruction[31]}}, instruction[31:25], instruction[11:7]};
      end
7'b1100011:
      begin//B TYPE
func3 = instruction[14:12];
source_reg_1 = instruction[19:15];
source_reg_2 = instruction[24:20];
immediate = {{19{instruction[31]}}, instruction[31], instruction[7], instruction[30:25], instruction[11:8], 1'b0};  
      end
 default:
   begin
     destination_reg=0;
     func3=0;
     source_reg_1=0;
     source_reg_2=0;
     func7=0;
     immediate=0;
   end
      endcase
    end
endmodule

design/instruction_memory.v
module instruction_memory(input [31:0] pc,output reg [31:0] instruction);
reg [31:0] memory[0:15];
initial begin
    memory[0] = 32'h003100B3;
    memory[1] = 32'h00510113;
    memory[2] = 32'h00112023;
    memory[3] = 32'h00000063;
end
always @(*) begin
    if(pc[5:2] < 4)
        instruction = memory[pc[5:2]];
    else
        instruction = 32'b0;
end
endmodule

design/program_counter.v
module program_counter(input clk,input reset,output reg [31:0] pc);
always @(posedge clk or posedge reset) begin
    if(reset)
        pc <= 0;
    else
        pc <= pc + 4;
end
endmodule

design/processor_top.v
module processor_top(input clk,input reset,output [31:0] pc,output [31:0] instruction,output [31:0] result);

wire [31:0] immediate;
wire reg_write;
wire mem_read;
wire mem_write;
wire alu_src;
wire branch;
wire [6:0] opcode;
wire [4:0] destination_reg;
wire [2:0] func3;
wire [4:0] source_reg_1;
wire [4:0] source_reg_2;
wire [6:0] func7;
wire [1:0] alu_op;
wire [2:0] alu_sel;
wire [31:0] A;
wire [31:0] B;
wire [31:0] read_data1;
wire [31:0] read_data2;
wire [31:0] address;
wire [31:0] read_data;
wire [31:0] mem_write_data;
wire [31:0] reg_write_data;
  
assign A = read_data1;

assign B = (alu_src) ? immediate : read_data2;

assign address = result;

assign mem_write_data = read_data2;

assign reg_write_data = (mem_read) ? read_data : result;

program_counter pc1(.clk(clk),.reset(reset),.pc(pc));

  instruction_memory im1(.pc(pc),.instruction(instruction));

complete_riscv_decoder crd(.instruction(instruction),.opcode(opcode),.destination_reg(destination_reg),.func3(func3),.source_reg_1(source_reg_1),.source_reg_2(source_reg_2),.func7(func7),.immediate(immediate));

register_file rf1(.clk(clk),.reg_write(reg_write),.source_reg_1(source_reg_1),.source_reg_2(source_reg_2),.destination_reg(destination_reg),.write_data(reg_write_data),.read_data1(read_data1),.read_data2(read_data2));

alu_control ac1(.alu_op(alu_op),.func3(func3), .func7(func7),.alu_sel(alu_sel));

data_memory dm1(.clk(clk),.mem_read(mem_read),.mem_write(mem_write),.write_data(mem_write_data),.address(address),.read_data(read_data));
                                                                              
 alu_32bit alu1(.A(A) ,.B(B) ,.alu_sel(alu_sel) ,.result(result));
  
 control_signal_generator csg(.opcode(opcode),.reg_write(reg_write),.mem_read(mem_read),.mem_write(mem_write),.alu_src(alu_src),.branch(branch),.alu_op(alu_op));
  
endmodule

testbench/processor_top_tb.v
module processor_top_tb;
reg clk, reset;
processor_top uut(.clk(clk),.reset(reset));

initial begin
  $dumpfile("processor_top.vcd");
  $dumpvars(0, processor_top_tb);
    clk = 0;
    reset = 1;
    #10;
    reset = 0;
    #500;
  $finish;
end
always #5 clk = ~clk;
endmodule

processor_top.vcd
$date
	Sat Jul 04 14:46:33 2026
$end
$version
	Icarus Verilog
$end
$timescale
	1s
$end
$scope module processor_top_tb $end
$var reg 1 ! clk $end
$var reg 1 " reset $end
$scope module uut $end
$var wire 32 # A [31:0] $end
$var wire 32 $ address [31:0] $end
$var wire 1 ! clk $end
$var wire 32 % mem_write_data [31:0] $end
$var wire 1 " reset $end
$var wire 5 & source_reg_2 [4:0] $end
$var wire 5 ' source_reg_1 [4:0] $end
$var wire 32 ( result [31:0] $end
$var wire 32 ) reg_write_data [31:0] $end
$var wire 1 * reg_write $end
$var wire 32 + read_data2 [31:0] $end
$var wire 32 , read_data1 [31:0] $end
$var wire 32 - read_data [31:0] $end
$var wire 32 . pc [31:0] $end
$var wire 7 / opcode [6:0] $end
$var wire 1 0 mem_write $end
$var wire 1 1 mem_read $end
$var wire 32 2 instruction [31:0] $end
$var wire 32 3 immediate [31:0] $end
$var wire 7 4 func7 [6:0] $end
$var wire 3 5 func3 [2:0] $end
$var wire 5 6 destination_reg [4:0] $end
$var wire 1 7 branch $end
$var wire 1 8 alu_src $end
$var wire 3 9 alu_sel [2:0] $end
$var wire 2 : alu_op [1:0] $end
$var wire 32 ; B [31:0] $end
$scope module ac1 $end
$var wire 7 < func7 [6:0] $end
$var wire 3 = func3 [2:0] $end
$var wire 2 > alu_op [1:0] $end
$var reg 3 ? alu_sel [2:0] $end
$upscope $end
$scope module alu1 $end
$var wire 32 @ A [31:0] $end
$var wire 32 A B [31:0] $end
$var wire 3 B alu_sel [2:0] $end
$var reg 32 C result [31:0] $end
$upscope $end
$scope module crd $end
$var wire 32 D instruction [31:0] $end
$var reg 5 E destination_reg [4:0] $end
$var reg 3 F func3 [2:0] $end
$var reg 7 G func7 [6:0] $end
$var reg 32 H immediate [31:0] $end
$var reg 7 I opcode [6:0] $end
$var reg 5 J source_reg_1 [4:0] $end
$var reg 5 K source_reg_2 [4:0] $end
$upscope $end
$scope module csg $end
$var wire 7 L opcode [6:0] $end
$var reg 2 M alu_op [1:0] $end
$var reg 1 8 alu_src $end
$var reg 1 7 branch $end
$var reg 1 1 mem_read $end
$var reg 1 0 mem_write $end
$var reg 1 * reg_write $end
$upscope $end
$scope module dm1 $end
$var wire 32 N address [31:0] $end
$var wire 1 ! clk $end
$var wire 1 1 mem_read $end
$var wire 1 0 mem_write $end
$var wire 32 O write_data [31:0] $end
$var reg 32 P read_data [31:0] $end
$var integer 32 Q i [31:0] $end
$upscope $end
$scope module im1 $end
$var wire 32 R pc [31:0] $end
$var reg 32 S instruction [31:0] $end
$upscope $end
$scope module pc1 $end
$var wire 1 ! clk $end
$var wire 1 " reset $end
$var reg 32 T pc [31:0] $end
$upscope $end
$scope module rf1 $end
$var wire 1 ! clk $end
$var wire 5 U destination_reg [4:0] $end
$var wire 1 * reg_write $end
$var wire 5 V source_reg_1 [4:0] $end
$var wire 5 W source_reg_2 [4:0] $end
$var wire 32 X write_data [31:0] $end
$var wire 32 Y read_data2 [31:0] $end
$var wire 32 Z read_data1 [31:0] $end
$var integer 32 [ i [31:0] $end
$upscope $end
$upscope $end
$upscope $end
$enddefinitions $end
#0
$dumpvars
b100000 [
b0 Z
b0 Y
b0 X
b11 W
b10 V
b1 U
b0 T
b1100010000000010110011 S
b0 R
b100000 Q
b0 P
b0 O
b0 N
b10 M
b110011 L
b11 K
b10 J
b110011 I
b0 H
b0 G
b0 F
b1 E
b1100010000000010110011 D
b0 C
b0 B
b0 A
b0 @
b0 ?
b10 >
b0 =
b0 <
b0 ;
b10 :
b0 9
08
07
b1 6
b0 5
b0 4
b0 3
b1100010000000010110011 2
01
00
b110011 /
b0 .
b0 -
b0 ,
b0 +
1*
b0 )
b0 (
b10 '
b11 &
b0 %
b0 $
b0 #
1"
0!
$end
#5
1!
#10
0!
0"
#15
b101 )
b101 X
b101 $
b101 N
b101 (
b101 C
b101 ;
b101 A
18
b0 :
b0 >
b0 M
1*
b101 3
b101 H
b0 &
b0 K
b0 W
b10 '
b10 J
b10 V
b10 6
b10 E
b10 U
b10011 /
b10011 I
b10011 L
b10100010000000100010011 2
b10100010000000100010011 D
b10100010000000100010011 S
b100 .
b100 R
b100 T
1!
#20
0!
#25
b101 )
b101 X
b0 ;
b0 A
10
18
0*
b101 $
b101 N
b101 (
b101 C
b1 &
b1 K
b1 W
b10 5
b10 =
b10 F
b0 3
b0 H
b10 '
b10 J
b10 V
b0 6
b0 E
b0 U
b100011 /
b100011 I
b100011 L
b101 #
b101 @
b101 ,
b101 Z
b100010010000000100011 2
b100010010000000100011 D
b100010010000000100011 S
b1000 .
b1000 R
b1000 T
1!
#30
0!
#35
b0 )
b0 X
b0 $
b0 N
b0 (
b0 C
b0 #
b0 @
b0 ,
b0 Z
b1 9
b1 ?
b1 B
b1 :
b1 >
b1 M
17
08
00
b0 &
b0 K
b0 W
b0 '
b0 J
b0 V
b0 5
b0 =
b0 F
b1100011 /
b1100011 I
b1100011 L
b1100011 2
b1100011 D
b1100011 S
b1100 .
b1100 R
b1100 T
1!
#40
0!
#45
b0 9
b0 ?
b0 B
b0 :
b0 >
b0 M
07
b0 /
b0 I
b0 L
b0 2
b0 D
b0 S
b10000 .
b10000 R
b10000 T
1!
#50
0!
#55
b10100 .
b10100 R
b10100 T
1!
#60
0!
#65
b11000 .
b11000 R
b11000 T
1!
#70
0!
#75
b11100 .
b11100 R
b11100 T
1!
#80
0!
#85
b100000 .
b100000 R
b100000 T
1!
#90
0!
#95
b100100 .
b100100 R
b100100 T
1!
#100
0!
#105
b101000 .
b101000 R
b101000 T
1!
